base00/__init__.py
base00/memoria.py
base00-0.0.1.dist-info/METADATA
base00-0.0.1.dist-info/WHEEL
base00-0.0.1.dist-info/top_level.txt
base00-0.0.1.dist-info/RECORD
